{
  "$schema": "./node_modules/@stryker-mutator/core/schema/stryker-schema.json",
  "plugins": ["@stryker-mutator/typescript-checker"],
  "testRunner": "command",
  "checkers": ["typescript"],
  "tsconfigFile": "tsconfig.stryker.json",
  "mutate": [
    "packages/utils/src/**/*.ts",
    "apps/website/src/lib/*.ts",
    "apps/website/src/components/*.tsx"
  ],
  "reporters": ["clear-text", "html", "progress"],
  "coverageAnalysis": "off",
  "incremental": true,
  "incrementalFile": "reports/mutation/mutation-incremental.json",
  "cleanTempDir": "always",
  "concurrency": 2,
  "commandRunner": {
    "command": "vp test"
  },
  "typescriptChecker": {
    "prioritizePerformanceOverAccuracy": true
  }
}
